{
  "points": [
    {
      "x": 139,
      "y": 223,
      "t": 417750,
      "c": 63519
    },
    {
      "x": 137,
      "y": 227,
      "t": 417767,
      "c": 63519
    },
    {
      "x": 137,
      "y": 228,
      "t": 417801,
      "c": 63519
    },
    {
      "x": 137,
      "y": 232,
      "t": 417842,
      "c": 63519
    },
    {
      "x": 135,
      "y": 234,
      "t": 417884,
      "c": 63519
    },
    {
      "x": 133,
      "y": 237,
      "t": 417925,
      "c": 63519
    },
    {
      "x": 134,
      "y": 240,
      "t": 417967,
      "c": 63519
    },
    {
      "x": 134,
      "y": 242,
      "t": 418009,
      "c": 63519
    },
    {
      "x": 134,
      "y": 245,
      "t": 418050,
      "c": 63519
    },
    {
      "x": 136,
      "y": 248,
      "t": 418092,
      "c": 63519
    },
    {
      "x": 136,
      "y": 249,
      "t": 418134,
      "c": 63519
    },
    {
      "x": 139,
      "y": 252,
      "t": 418174,
      "c": 63519
    },
    {
      "x": 139,
      "y": 255,
      "t": 418216,
      "c": 63519
    },
    {
      "x": 142,
      "y": 258,
      "t": 418257,
      "c": 63519
    },
    {
      "x": 143,
      "y": 262,
      "t": 418321,
      "c": 63519
    },
    {
      "x": 148,
      "y": 264,
      "t": 418376,
      "c": 63519
    },
    {
      "x": 148,
      "y": 265,
      "t": 418382,
      "c": 63519
    },
    {
      "x": 151,
      "y": 266,
      "t": 418424,
      "c": 63519
    },
    {
      "x": 153,
      "y": 270,
      "t": 418466,
      "c": 63519
    },
    {
      "x": 154,
      "y": 272,
      "t": 418507,
      "c": 63519
    },
    {
      "x": 158,
      "y": 273,
      "t": 418549,
      "c": 63519
    },
    {
      "x": 160,
      "y": 274,
      "t": 418590,
      "c": 63519
    },
    {
      "x": 163,
      "y": 276,
      "t": 418632,
      "c": 63519
    },
    {
      "x": 166,
      "y": 277,
      "t": 418674,
      "c": 63519
    },
    {
      "x": 169,
      "y": 279,
      "t": 418715,
      "c": 63519
    },
    {
      "x": 172,
      "y": 280,
      "t": 418757,
      "c": 63519
    },
    {
      "x": 175,
      "y": 281,
      "t": 418799,
      "c": 63519
    },
    {
      "x": 180,
      "y": 281,
      "t": 418840,
      "c": 63519
    },
    {
      "x": 184,
      "y": 282,
      "t": 418882,
      "c": 63519
    },
    {
      "x": 189,
      "y": 283,
      "t": 418923,
      "c": 63519
    },
    {
      "x": 191,
      "y": 283,
      "t": 418965,
      "c": 63519
    },
    {
      "x": 195,
      "y": 283,
      "t": 419007,
      "c": 63519
    },
    {
      "x": 197,
      "y": 282,
      "t": 419048,
      "c": 63519
    },
    {
      "x": 199,
      "y": 282,
      "t": 419090,
      "c": 63519
    },
    {
      "x": 201,
      "y": 282,
      "t": 419132,
      "c": 63519
    },
    {
      "x": 204,
      "y": 281,
      "t": 419173,
      "c": 63519
    },
    {
      "x": 205,
      "y": 281,
      "t": 419215,
      "c": 63519
    },
    {
      "x": 208,
      "y": 280,
      "t": 419256,
      "c": 63519
    },
    {
      "x": 212,
      "y": 280,
      "t": 419298,
      "c": 63519
    },
    {
      "x": 215,
      "y": 276,
      "t": 419344,
      "c": 63519
    },
    {
      "x": 216,
      "y": 275,
      "t": 419381,
      "c": 63519
    },
    {
      "x": 219,
      "y": 274,
      "t": 419423,
      "c": 63519
    },
    {
      "x": 221,
      "y": 272,
      "t": 419465,
      "c": 63519
    },
    {
      "x": 221,
      "y": 271,
      "t": 419506,
      "c": 63519
    },
    {
      "x": 225,
      "y": 269,
      "t": 419548,
      "c": 63519
    },
    {
      "x": 227,
      "y": 266,
      "t": 419589,
      "c": 63519
    },
    {
      "x": 227,
      "y": 265,
      "t": 419631,
      "c": 63519
    },
    {
      "x": 229,
      "y": 263,
      "t": 419673,
      "c": 63519
    },
    {
      "x": 231,
      "y": 258,
      "t": 419714,
      "c": 63519
    },
    {
      "x": 233,
      "y": 256,
      "t": 419756,
      "c": 63519
    },
    {
      "x": 235,
      "y": 252,
      "t": 419798,
      "c": 63519
    },
    {
      "x": 236,
      "y": 250,
      "t": 419838,
      "c": 63519
    },
    {
      "x": 237,
      "y": 248,
      "t": 419880,
      "c": 63519
    },
    {
      "x": 236,
      "y": 244,
      "t": 419921,
      "c": 63519
    },
    {
      "x": 238,
      "y": 244,
      "t": 419963,
      "c": 63519
    },
    {
      "x": 240,
      "y": 241,
      "t": 420005,
      "c": 63519
    },
    {
      "x": 238,
      "y": 238,
      "t": 420046,
      "c": 63519
    },
    {
      "x": 239,
      "y": 236,
      "t": 420088,
      "c": 63519
    },
    {
      "x": 238,
      "y": 233,
      "t": 420130,
      "c": 63519
    },
    {
      "x": 240,
      "y": 229,
      "t": 420171,
      "c": 63519
    },
    {
      "x": 241,
      "y": 227,
      "t": 420213,
      "c": 63519
    },
    {
      "x": 241,
      "y": 224,
      "t": 420254,
      "c": 63519
    },
    {
      "x": 238,
      "y": 221,
      "t": 420296,
      "c": 63519
    },
    {
      "x": 237,
      "y": 217,
      "t": 420338,
      "c": 63519
    },
    {
      "x": 238,
      "y": 216,
      "t": 420379,
      "c": 63519
    },
    {
      "x": 237,
      "y": 213,
      "t": 420421,
      "c": 63519
    },
    {
      "x": 237,
      "y": 210,
      "t": 420463,
      "c": 63519
    },
    {
      "x": 233,
      "y": 208,
      "t": 420504,
      "c": 63519
    },
    {
      "x": 231,
      "y": 203,
      "t": 420546,
      "c": 63519
    },
    {
      "x": 227,
      "y": 200,
      "t": 420587,
      "c": 63519
    },
    {
      "x": 222,
      "y": 198,
      "t": 420629,
      "c": 63519
    },
    {
      "x": 217,
      "y": 194,
      "t": 420671,
      "c": 63519
    },
    {
      "x": 213,
      "y": 193,
      "t": 420712,
      "c": 63519
    },
    {
      "x": 206,
      "y": 192,
      "t": 420754,
      "c": 63519
    },
    {
      "x": 205,
      "y": 190,
      "t": 420796,
      "c": 63519
    },
    {
      "x": 205,
      "y": 188,
      "t": 420837,
      "c": 63519
    },
    {
      "x": 202,
      "y": 189,
      "t": 420879,
      "c": 63519
    },
    {
      "x": 197,
      "y": 188,
      "t": 420920,
      "c": 63519
    },
    {
      "x": 198,
      "y": 188,
      "t": 420962,
      "c": 63519
    },
    {
      "x": 195,
      "y": 187,
      "t": 421004,
      "c": 63519
    },
    {
      "x": 193,
      "y": 185,
      "t": 421045,
      "c": 63519
    },
    {
      "x": 190,
      "y": 186,
      "t": 421087,
      "c": 63519
    },
    {
      "x": 188,
      "y": 187,
      "t": 421129,
      "c": 63519
    },
    {
      "x": 183,
      "y": 187,
      "t": 421170,
      "c": 63519
    },
    {
      "x": 179,
      "y": 188,
      "t": 421212,
      "c": 63519
    },
    {
      "x": 177,
      "y": 188,
      "t": 421253,
      "c": 63519
    },
    {
      "x": 177,
      "y": 190,
      "t": 421295,
      "c": 63519
    },
    {
      "x": 174,
      "y": 191,
      "t": 421345,
      "c": 63519
    },
    {
      "x": 174,
      "y": 191,
      "t": 421378,
      "c": 63519
    },
    {
      "x": 171,
      "y": 192,
      "t": 421420,
      "c": 63519
    },
    {
      "x": 172,
      "y": 193,
      "t": 421462,
      "c": 63519
    },
    {
      "x": 170,
      "y": 193,
      "t": 421502,
      "c": 63519
    },
    {
      "x": 168,
      "y": 193,
      "t": 421544,
      "c": 63519
    },
    {
      "x": 166,
      "y": 195,
      "t": 421585,
      "c": 63519
    },
    {
      "x": 164,
      "y": 194,
      "t": 421627,
      "c": 63519
    },
    {
      "x": 163,
      "y": 196,
      "t": 421669,
      "c": 63519
    },
    {
      "x": 162,
      "y": 195,
      "t": 421710,
      "c": 63519
    },
    {
      "x": 159,
      "y": 197,
      "t": 421752,
      "c": 63519
    },
    {
      "x": 159,
      "y": 198,
      "t": 421794,
      "c": 63519
    },
    {
      "x": 157,
      "y": 198,
      "t": 421835,
      "c": 63519
    },
    {
      "x": 153,
      "y": 200,
      "t": 421877,
      "c": 63519
    },
    {
      "x": 153,
      "y": 201,
      "t": 421918,
      "c": 63519
    },
    {
      "x": 151,
      "y": 203,
      "t": 421960,
      "c": 63519
    },
    {
      "x": 150,
      "y": 204,
      "t": 422002,
      "c": 63519
    },
    {
      "x": 150,
      "y": 205,
      "t": 422043,
      "c": 63519
    },
    {
      "x": 147,
      "y": 206,
      "t": 422085,
      "c": 63519
    },
    {
      "x": 146,
      "y": 207,
      "t": 422127,
      "c": 63519
    },
    {
      "x": 145,
      "y": 208,
      "t": 422168,
      "c": 63519
    },
    {
      "x": 142,
      "y": 209,
      "t": 422210,
      "c": 63519
    },
    {
      "x": 143,
      "y": 211,
      "t": 422251,
      "c": 63519
    },
    {
      "x": 143,
      "y": 213,
      "t": 422293,
      "c": 63519
    },
    {
      "x": 140,
      "y": 214,
      "t": 422335,
      "c": 63519
    },
    {
      "x": 140,
      "y": 218,
      "t": 422376,
      "c": 63519
    },
    {
      "x": 137,
      "y": 222,
      "t": 422418,
      "c": 63519
    },
    {
      "x": 135,
      "y": 227,
      "t": 422460,
      "c": 63519
    }
  ],
  "label": "circle",
  "confidence": 1.0
}