{
  "points": [
    {
      "x": 77,
      "y": 204,
      "t": 28486,
      "c": 65504
    },
    {
      "x": 78,
      "y": 200,
      "t": 28503,
      "c": 65504
    },
    {
      "x": 76,
      "y": 203,
      "t": 28531,
      "c": 65504
    },
    {
      "x": 75,
      "y": 203,
      "t": 28571,
      "c": 65504
    },
    {
      "x": 76,
      "y": 205,
      "t": 28611,
      "c": 65504
    },
    {
      "x": 75,
      "y": 209,
      "t": 28695,
      "c": 65504
    },
    {
      "x": 74,
      "y": 209,
      "t": 28700,
      "c": 65504
    },
    {
      "x": 74,
      "y": 209,
      "t": 28729,
      "c": 65504
    },
    {
      "x": 74,
      "y": 211,
      "t": 28769,
      "c": 65504
    },
    {
      "x": 75,
      "y": 213,
      "t": 28809,
      "c": 65504
    },
    {
      "x": 74,
      "y": 214,
      "t": 28848,
      "c": 65504
    },
    {
      "x": 75,
      "y": 216,
      "t": 28888,
      "c": 65504
    },
    {
      "x": 78,
      "y": 227,
      "t": 28939,
      "c": 65504
    },
    {
      "x": 77,
      "y": 223,
      "t": 28966,
      "c": 65504
    },
    {
      "x": 78,
      "y": 225,
      "t": 29006,
      "c": 65504
    },
    {
      "x": 78,
      "y": 229,
      "t": 29045,
      "c": 65504
    },
    {
      "x": 79,
      "y": 233,
      "t": 29085,
      "c": 65504
    },
    {
      "x": 81,
      "y": 233,
      "t": 29124,
      "c": 65504
    },
    {
      "x": 82,
      "y": 232,
      "t": 29164,
      "c": 65504
    },
    {
      "x": 86,
      "y": 239,
      "t": 29204,
      "c": 65504
    },
    {
      "x": 87,
      "y": 240,
      "t": 29243,
      "c": 65504
    },
    {
      "x": 88,
      "y": 239,
      "t": 29283,
      "c": 65504
    },
    {
      "x": 91,
      "y": 242,
      "t": 29322,
      "c": 65504
    },
    {
      "x": 92,
      "y": 245,
      "t": 29362,
      "c": 65504
    },
    {
      "x": 94,
      "y": 247,
      "t": 29402,
      "c": 65504
    },
    {
      "x": 97,
      "y": 245,
      "t": 29441,
      "c": 65504
    },
    {
      "x": 98,
      "y": 244,
      "t": 29480,
      "c": 65504
    },
    {
      "x": 100,
      "y": 252,
      "t": 29520,
      "c": 65504
    },
    {
      "x": 101,
      "y": 249,
      "t": 29561,
      "c": 65504
    },
    {
      "x": 107,
      "y": 250,
      "t": 29602,
      "c": 65504
    },
    {
      "x": 110,
      "y": 248,
      "t": 29642,
      "c": 65504
    },
    {
      "x": 112,
      "y": 252,
      "t": 29683,
      "c": 65504
    },
    {
      "x": 117,
      "y": 252,
      "t": 29723,
      "c": 65504
    },
    {
      "x": 119,
      "y": 250,
      "t": 29764,
      "c": 65504
    },
    {
      "x": 126,
      "y": 254,
      "t": 29843,
      "c": 65504
    },
    {
      "x": 130,
      "y": 253,
      "t": 29884,
      "c": 65504
    },
    {
      "x": 134,
      "y": 250,
      "t": 29895,
      "c": 65504
    },
    {
      "x": 136,
      "y": 249,
      "t": 29940,
      "c": 65504
    },
    {
      "x": 139,
      "y": 246,
      "t": 29967,
      "c": 65504
    },
    {
      "x": 143,
      "y": 248,
      "t": 30020,
      "c": 65504
    },
    {
      "x": 146,
      "y": 257,
      "t": 30064,
      "c": 65504
    },
    {
      "x": 147,
      "y": 248,
      "t": 30089,
      "c": 65504
    },
    {
      "x": 152,
      "y": 250,
      "t": 30129,
      "c": 65504
    },
    {
      "x": 163,
      "y": 245,
      "t": 30278,
      "c": 65504
    },
    {
      "x": 164,
      "y": 241,
      "t": 30280,
      "c": 65504
    },
    {
      "x": 164,
      "y": 244,
      "t": 30313,
      "c": 65504
    },
    {
      "x": 167,
      "y": 245,
      "t": 30354,
      "c": 65504
    },
    {
      "x": 168,
      "y": 237,
      "t": 30405,
      "c": 65504
    },
    {
      "x": 172,
      "y": 235,
      "t": 30441,
      "c": 65504
    },
    {
      "x": 174,
      "y": 232,
      "t": 30489,
      "c": 65504
    },
    {
      "x": 179,
      "y": 228,
      "t": 30532,
      "c": 65504
    },
    {
      "x": 177,
      "y": 227,
      "t": 30557,
      "c": 65504
    },
    {
      "x": 178,
      "y": 231,
      "t": 30597,
      "c": 65504
    },
    {
      "x": 181,
      "y": 229,
      "t": 30638,
      "c": 65504
    },
    {
      "x": 182,
      "y": 226,
      "t": 30686,
      "c": 65504
    },
    {
      "x": 186,
      "y": 218,
      "t": 30743,
      "c": 65504
    },
    {
      "x": 186,
      "y": 215,
      "t": 30787,
      "c": 65504
    },
    {
      "x": 185,
      "y": 215,
      "t": 30804,
      "c": 65504
    },
    {
      "x": 190,
      "y": 202,
      "t": 30873,
      "c": 65504
    },
    {
      "x": 188,
      "y": 201,
      "t": 30915,
      "c": 65504
    },
    {
      "x": 187,
      "y": 200,
      "t": 30922,
      "c": 65504
    },
    {
      "x": 190,
      "y": 195,
      "t": 30962,
      "c": 65504
    },
    {
      "x": 190,
      "y": 187,
      "t": 31053,
      "c": 65504
    },
    {
      "x": 189,
      "y": 189,
      "t": 31064,
      "c": 65504
    },
    {
      "x": 190,
      "y": 185,
      "t": 31088,
      "c": 65504
    },
    {
      "x": 188,
      "y": 185,
      "t": 31175,
      "c": 65504
    },
    {
      "x": 187,
      "y": 177,
      "t": 31216,
      "c": 65504
    },
    {
      "x": 187,
      "y": 176,
      "t": 31219,
      "c": 65504
    },
    {
      "x": 184,
      "y": 181,
      "t": 31251,
      "c": 65504
    },
    {
      "x": 182,
      "y": 176,
      "t": 31292,
      "c": 65504
    },
    {
      "x": 181,
      "y": 174,
      "t": 31333,
      "c": 65504
    },
    {
      "x": 177,
      "y": 170,
      "t": 31373,
      "c": 65504
    },
    {
      "x": 169,
      "y": 164,
      "t": 31464,
      "c": 65504
    },
    {
      "x": 168,
      "y": 165,
      "t": 31469,
      "c": 65504
    },
    {
      "x": 168,
      "y": 165,
      "t": 31499,
      "c": 65504
    },
    {
      "x": 165,
      "y": 160,
      "t": 31540,
      "c": 65504
    },
    {
      "x": 162,
      "y": 157,
      "t": 31580,
      "c": 65504
    },
    {
      "x": 159,
      "y": 161,
      "t": 31621,
      "c": 65504
    },
    {
      "x": 154,
      "y": 157,
      "t": 31673,
      "c": 65504
    },
    {
      "x": 152,
      "y": 164,
      "t": 31702,
      "c": 65504
    },
    {
      "x": 145,
      "y": 155,
      "t": 31759,
      "c": 65504
    },
    {
      "x": 143,
      "y": 160,
      "t": 31782,
      "c": 65504
    },
    {
      "x": 141,
      "y": 162,
      "t": 31823,
      "c": 65504
    },
    {
      "x": 135,
      "y": 156,
      "t": 31864,
      "c": 65504
    },
    {
      "x": 130,
      "y": 152,
      "t": 31904,
      "c": 65504
    },
    {
      "x": 128,
      "y": 154,
      "t": 31945,
      "c": 65504
    },
    {
      "x": 121,
      "y": 161,
      "t": 31985,
      "c": 65504
    },
    {
      "x": 118,
      "y": 160,
      "t": 32026,
      "c": 65504
    },
    {
      "x": 113,
      "y": 154,
      "t": 32067,
      "c": 65504
    },
    {
      "x": 108,
      "y": 156,
      "t": 32107,
      "c": 65504
    },
    {
      "x": 106,
      "y": 157,
      "t": 32148,
      "c": 65504
    },
    {
      "x": 102,
      "y": 158,
      "t": 32189,
      "c": 65504
    },
    {
      "x": 100,
      "y": 161,
      "t": 32229,
      "c": 65504
    },
    {
      "x": 97,
      "y": 157,
      "t": 32269,
      "c": 65504
    },
    {
      "x": 93,
      "y": 165,
      "t": 32308,
      "c": 65504
    },
    {
      "x": 91,
      "y": 162,
      "t": 32348,
      "c": 65504
    },
    {
      "x": 88,
      "y": 167,
      "t": 32387,
      "c": 65504
    },
    {
      "x": 85,
      "y": 169,
      "t": 32427,
      "c": 65504
    },
    {
      "x": 85,
      "y": 173,
      "t": 32466,
      "c": 65504
    },
    {
      "x": 83,
      "y": 173,
      "t": 32505,
      "c": 65504
    },
    {
      "x": 82,
      "y": 175,
      "t": 32545,
      "c": 65504
    },
    {
      "x": 79,
      "y": 185,
      "t": 32584,
      "c": 65504
    },
    {
      "x": 78,
      "y": 186,
      "t": 32624,
      "c": 65504
    },
    {
      "x": 76,
      "y": 191,
      "t": 32664,
      "c": 65504
    },
    {
      "x": 76,
      "y": 188,
      "t": 32703,
      "c": 65504
    },
    {
      "x": 71,
      "y": 196,
      "t": 32743,
      "c": 65504
    },
    {
      "x": 68,
      "y": 195,
      "t": 32782,
      "c": 65504
    },
    {
      "x": 73,
      "y": 206,
      "t": 32822,
      "c": 65504
    },
    {
      "x": 72,
      "y": 219,
      "t": 32862,
      "c": 65504
    }
  ],
  "label": "circle",
  "confidence": 1.0
}