{
  "label": "circle",
  "timestamp": "20251106_022929",
  "num_points": 142,
  "points": [
    {
      "x": 26,
      "y": 268,
      "t": 1393871,
      "c": 31
    },
    {
      "x": 25,
      "y": 273,
      "t": 1393885,
      "c": 31
    },
    {
      "x": 23,
      "y": 273,
      "t": 1393914,
      "c": 31
    },
    {
      "x": 26,
      "y": 269,
      "t": 1393952,
      "c": 31
    },
    {
      "x": 24,
      "y": 274,
      "t": 1393991,
      "c": 31
    },
    {
      "x": 23,
      "y": 276,
      "t": 1394029,
      "c": 31
    },
    {
      "x": 21,
      "y": 279,
      "t": 1394068,
      "c": 31
    },
    {
      "x": 19,
      "y": 283,
      "t": 1394107,
      "c": 31
    },
    {
      "x": 17,
      "y": 287,
      "t": 1394145,
      "c": 31
    },
    {
      "x": 18,
      "y": 297,
      "t": 1394225,
      "c": 31
    },
    {
      "x": 19,
      "y": 296,
      "t": 1394231,
      "c": 31
    },
    {
      "x": 20,
      "y": 300,
      "t": 1394296,
      "c": 31
    },
    {
      "x": 20,
      "y": 300,
      "t": 1394299,
      "c": 31
    },
    {
      "x": 20,
      "y": 299,
      "t": 1394337,
      "c": 31
    },
    {
      "x": 20,
      "y": 301,
      "t": 1394376,
      "c": 31
    },
    {
      "x": 20,
      "y": 302,
      "t": 1394414,
      "c": 31
    },
    {
      "x": 21,
      "y": 305,
      "t": 1394453,
      "c": 31
    },
    {
      "x": 24,
      "y": 308,
      "t": 1394491,
      "c": 31
    },
    {
      "x": 25,
      "y": 309,
      "t": 1394530,
      "c": 31
    },
    {
      "x": 25,
      "y": 310,
      "t": 1394569,
      "c": 31
    },
    {
      "x": 25,
      "y": 313,
      "t": 1394607,
      "c": 31
    },
    {
      "x": 24,
      "y": 314,
      "t": 1394646,
      "c": 31
    },
    {
      "x": 27,
      "y": 316,
      "t": 1394683,
      "c": 31
    },
    {
      "x": 30,
      "y": 319,
      "t": 1394724,
      "c": 31
    },
    {
      "x": 29,
      "y": 319,
      "t": 1394764,
      "c": 31
    },
    {
      "x": 31,
      "y": 320,
      "t": 1394799,
      "c": 31
    },
    {
      "x": 35,
      "y": 322,
      "t": 1394845,
      "c": 31
    },
    {
      "x": 35,
      "y": 323,
      "t": 1394876,
      "c": 31
    },
    {
      "x": 37,
      "y": 323,
      "t": 1394915,
      "c": 31
    },
    {
      "x": 37,
      "y": 325,
      "t": 1394953,
      "c": 31
    },
    {
      "x": 38,
      "y": 323,
      "t": 1394992,
      "c": 31
    },
    {
      "x": 36,
      "y": 328,
      "t": 1395031,
      "c": 31
    },
    {
      "x": 43,
      "y": 326,
      "t": 1395068,
      "c": 31
    },
    {
      "x": 43,
      "y": 329,
      "t": 1395107,
      "c": 31
    },
    {
      "x": 44,
      "y": 330,
      "t": 1395145,
      "c": 31
    },
    {
      "x": 48,
      "y": 330,
      "t": 1395184,
      "c": 31
    },
    {
      "x": 46,
      "y": 331,
      "t": 1395222,
      "c": 31
    },
    {
      "x": 49,
      "y": 331,
      "t": 1395261,
      "c": 31
    },
    {
      "x": 51,
      "y": 333,
      "t": 1395300,
      "c": 31
    },
    {
      "x": 53,
      "y": 333,
      "t": 1395338,
      "c": 31
    },
    {
      "x": 53,
      "y": 334,
      "t": 1395377,
      "c": 31
    },
    {
      "x": 56,
      "y": 335,
      "t": 1395415,
      "c": 31
    },
    {
      "x": 59,
      "y": 336,
      "t": 1395456,
      "c": 31
    },
    {
      "x": 66,
      "y": 336,
      "t": 1395531,
      "c": 31
    },
    {
      "x": 69,
      "y": 336,
      "t": 1395571,
      "c": 31
    },
    {
      "x": 65,
      "y": 341,
      "t": 1395581,
      "c": 31
    },
    {
      "x": 68,
      "y": 338,
      "t": 1395607,
      "c": 31
    },
    {
      "x": 70,
      "y": 338,
      "t": 1395647,
      "c": 31
    },
    {
      "x": 69,
      "y": 339,
      "t": 1395684,
      "c": 31
    },
    {
      "x": 72,
      "y": 338,
      "t": 1395723,
      "c": 31
    },
    {
      "x": 74,
      "y": 341,
      "t": 1395761,
      "c": 31
    },
    {
      "x": 75,
      "y": 339,
      "t": 1395800,
      "c": 31
    },
    {
      "x": 81,
      "y": 340,
      "t": 1395838,
      "c": 31
    },
    {
      "x": 82,
      "y": 339,
      "t": 1395876,
      "c": 31
    },
    {
      "x": 84,
      "y": 340,
      "t": 1395915,
      "c": 31
    },
    {
      "x": 85,
      "y": 340,
      "t": 1395959,
      "c": 31
    },
    {
      "x": 86,
      "y": 338,
      "t": 1395992,
      "c": 31
    },
    {
      "x": 87,
      "y": 336,
      "t": 1396031,
      "c": 31
    },
    {
      "x": 98,
      "y": 334,
      "t": 1396106,
      "c": 31
    },
    {
      "x": 98,
      "y": 334,
      "t": 1396109,
      "c": 31
    },
    {
      "x": 101,
      "y": 334,
      "t": 1396177,
      "c": 31
    },
    {
      "x": 98,
      "y": 335,
      "t": 1396186,
      "c": 31
    },
    {
      "x": 99,
      "y": 333,
      "t": 1396224,
      "c": 31
    },
    {
      "x": 103,
      "y": 331,
      "t": 1396263,
      "c": 31
    },
    {
      "x": 105,
      "y": 327,
      "t": 1396312,
      "c": 31
    },
    {
      "x": 107,
      "y": 327,
      "t": 1396342,
      "c": 31
    },
    {
      "x": 105,
      "y": 328,
      "t": 1396382,
      "c": 31
    },
    {
      "x": 108,
      "y": 326,
      "t": 1396421,
      "c": 31
    },
    {
      "x": 111,
      "y": 322,
      "t": 1396474,
      "c": 31
    },
    {
      "x": 112,
      "y": 319,
      "t": 1396506,
      "c": 31
    },
    {
      "x": 114,
      "y": 320,
      "t": 1396541,
      "c": 31
    },
    {
      "x": 114,
      "y": 318,
      "t": 1396580,
      "c": 31
    },
    {
      "x": 114,
      "y": 314,
      "t": 1396619,
      "c": 31
    },
    {
      "x": 112,
      "y": 311,
      "t": 1396659,
      "c": 31
    },
    {
      "x": 114,
      "y": 307,
      "t": 1396699,
      "c": 31
    },
    {
      "x": 113,
      "y": 309,
      "t": 1396742,
      "c": 31
    },
    {
      "x": 114,
      "y": 307,
      "t": 1396777,
      "c": 31
    },
    {
      "x": 115,
      "y": 305,
      "t": 1396816,
      "c": 31
    },
    {
      "x": 116,
      "y": 304,
      "t": 1396856,
      "c": 31
    },
    {
      "x": 118,
      "y": 301,
      "t": 1396896,
      "c": 31
    },
    {
      "x": 119,
      "y": 299,
      "t": 1396935,
      "c": 31
    },
    {
      "x": 119,
      "y": 298,
      "t": 1396975,
      "c": 31
    },
    {
      "x": 120,
      "y": 297,
      "t": 1397014,
      "c": 31
    },
    {
      "x": 120,
      "y": 296,
      "t": 1397054,
      "c": 31
    },
    {
      "x": 119,
      "y": 293,
      "t": 1397094,
      "c": 31
    },
    {
      "x": 120,
      "y": 292,
      "t": 1397133,
      "c": 31
    },
    {
      "x": 120,
      "y": 289,
      "t": 1397173,
      "c": 31
    },
    {
      "x": 121,
      "y": 283,
      "t": 1397254,
      "c": 31
    },
    {
      "x": 120,
      "y": 284,
      "t": 1397257,
      "c": 31
    },
    {
      "x": 120,
      "y": 284,
      "t": 1397291,
      "c": 31
    },
    {
      "x": 119,
      "y": 279,
      "t": 1397334,
      "c": 31
    },
    {
      "x": 119,
      "y": 278,
      "t": 1397370,
      "c": 31
    },
    {
      "x": 118,
      "y": 276,
      "t": 1397409,
      "c": 31
    },
    {
      "x": 118,
      "y": 274,
      "t": 1397449,
      "c": 31
    },
    {
      "x": 118,
      "y": 266,
      "t": 1397516,
      "c": 31
    },
    {
      "x": 117,
      "y": 266,
      "t": 1397528,
      "c": 31
    },
    {
      "x": 115,
      "y": 265,
      "t": 1397568,
      "c": 31
    },
    {
      "x": 117,
      "y": 260,
      "t": 1397607,
      "c": 31
    },
    {
      "x": 115,
      "y": 261,
      "t": 1397647,
      "c": 31
    },
    {
      "x": 113,
      "y": 258,
      "t": 1397686,
      "c": 31
    },
    {
      "x": 111,
      "y": 257,
      "t": 1397726,
      "c": 31
    },
    {
      "x": 109,
      "y": 254,
      "t": 1397766,
      "c": 31
    },
    {
      "x": 103,
      "y": 254,
      "t": 1397805,
      "c": 31
    },
    {
      "x": 107,
      "y": 251,
      "t": 1397844,
      "c": 31
    },
    {
      "x": 102,
      "y": 250,
      "t": 1397883,
      "c": 31
    },
    {
      "x": 93,
      "y": 249,
      "t": 1398003,
      "c": 31
    },
    {
      "x": 90,
      "y": 249,
      "t": 1398011,
      "c": 31
    },
    {
      "x": 89,
      "y": 248,
      "t": 1398033,
      "c": 31
    },
    {
      "x": 88,
      "y": 247,
      "t": 1398072,
      "c": 31
    },
    {
      "x": 86,
      "y": 248,
      "t": 1398111,
      "c": 31
    },
    {
      "x": 85,
      "y": 247,
      "t": 1398149,
      "c": 31
    },
    {
      "x": 84,
      "y": 247,
      "t": 1398188,
      "c": 31
    },
    {
      "x": 78,
      "y": 246,
      "t": 1398225,
      "c": 31
    },
    {
      "x": 77,
      "y": 245,
      "t": 1398264,
      "c": 31
    },
    {
      "x": 75,
      "y": 246,
      "t": 1398302,
      "c": 31
    },
    {
      "x": 74,
      "y": 245,
      "t": 1398341,
      "c": 31
    },
    {
      "x": 69,
      "y": 247,
      "t": 1398380,
      "c": 31
    },
    {
      "x": 68,
      "y": 248,
      "t": 1398418,
      "c": 31
    },
    {
      "x": 64,
      "y": 247,
      "t": 1398457,
      "c": 31
    },
    {
      "x": 64,
      "y": 247,
      "t": 1398495,
      "c": 31
    },
    {
      "x": 59,
      "y": 247,
      "t": 1398534,
      "c": 31
    },
    {
      "x": 57,
      "y": 248,
      "t": 1398572,
      "c": 31
    },
    {
      "x": 57,
      "y": 248,
      "t": 1398610,
      "c": 31
    },
    {
      "x": 55,
      "y": 249,
      "t": 1398678,
      "c": 31
    },
    {
      "x": 55,
      "y": 250,
      "t": 1398689,
      "c": 31
    },
    {
      "x": 52,
      "y": 249,
      "t": 1398726,
      "c": 31
    },
    {
      "x": 51,
      "y": 251,
      "t": 1398764,
      "c": 31
    },
    {
      "x": 50,
      "y": 249,
      "t": 1398803,
      "c": 31
    },
    {
      "x": 49,
      "y": 250,
      "t": 1398842,
      "c": 31
    },
    {
      "x": 41,
      "y": 255,
      "t": 1398880,
      "c": 31
    },
    {
      "x": 41,
      "y": 255,
      "t": 1398919,
      "c": 31
    },
    {
      "x": 37,
      "y": 255,
      "t": 1398957,
      "c": 31
    },
    {
      "x": 36,
      "y": 257,
      "t": 1398995,
      "c": 31
    },
    {
      "x": 37,
      "y": 258,
      "t": 1399033,
      "c": 31
    },
    {
      "x": 35,
      "y": 257,
      "t": 1399072,
      "c": 31
    },
    {
      "x": 34,
      "y": 258,
      "t": 1399111,
      "c": 31
    },
    {
      "x": 35,
      "y": 259,
      "t": 1399149,
      "c": 31
    },
    {
      "x": 32,
      "y": 260,
      "t": 1399188,
      "c": 31
    },
    {
      "x": 32,
      "y": 260,
      "t": 1399226,
      "c": 31
    },
    {
      "x": 26,
      "y": 267,
      "t": 1399286,
      "c": 31
    },
    {
      "x": 25,
      "y": 268,
      "t": 1399303,
      "c": 31
    },
    {
      "x": 23,
      "y": 269,
      "t": 1399342,
      "c": 31
    }
  ]
}