{
  "label": "triangle",
  "timestamp": "20251106_022234",
  "num_points": 71,
  "points": [
    {
      "x": 49,
      "y": 237,
      "t": 979519,
      "c": 2047
    },
    {
      "x": 52,
      "y": 238,
      "t": 979526,
      "c": 2047
    },
    {
      "x": 51,
      "y": 237,
      "t": 979564,
      "c": 2047
    },
    {
      "x": 52,
      "y": 235,
      "t": 979604,
      "c": 2047
    },
    {
      "x": 62,
      "y": 231,
      "t": 979692,
      "c": 2047
    },
    {
      "x": 63,
      "y": 234,
      "t": 979700,
      "c": 2047
    },
    {
      "x": 62,
      "y": 231,
      "t": 979724,
      "c": 2047
    },
    {
      "x": 63,
      "y": 231,
      "t": 979764,
      "c": 2047
    },
    {
      "x": 67,
      "y": 226,
      "t": 979804,
      "c": 2047
    },
    {
      "x": 70,
      "y": 222,
      "t": 979843,
      "c": 2047
    },
    {
      "x": 74,
      "y": 220,
      "t": 979904,
      "c": 2047
    },
    {
      "x": 74,
      "y": 218,
      "t": 979921,
      "c": 2047
    },
    {
      "x": 76,
      "y": 214,
      "t": 979961,
      "c": 2047
    },
    {
      "x": 79,
      "y": 211,
      "t": 980001,
      "c": 2047
    },
    {
      "x": 83,
      "y": 207,
      "t": 980040,
      "c": 2047
    },
    {
      "x": 87,
      "y": 200,
      "t": 980080,
      "c": 2047
    },
    {
      "x": 89,
      "y": 201,
      "t": 980119,
      "c": 2047
    },
    {
      "x": 96,
      "y": 190,
      "t": 980180,
      "c": 2047
    },
    {
      "x": 95,
      "y": 195,
      "t": 980198,
      "c": 2047
    },
    {
      "x": 103,
      "y": 186,
      "t": 980249,
      "c": 2047
    },
    {
      "x": 107,
      "y": 181,
      "t": 980281,
      "c": 2047
    },
    {
      "x": 110,
      "y": 181,
      "t": 980320,
      "c": 2047
    },
    {
      "x": 114,
      "y": 181,
      "t": 980361,
      "c": 2047
    },
    {
      "x": 118,
      "y": 170,
      "t": 980402,
      "c": 2047
    },
    {
      "x": 120,
      "y": 170,
      "t": 980442,
      "c": 2047
    },
    {
      "x": 128,
      "y": 166,
      "t": 980483,
      "c": 2047
    },
    {
      "x": 133,
      "y": 159,
      "t": 980549,
      "c": 2047
    },
    {
      "x": 132,
      "y": 157,
      "t": 980569,
      "c": 2047
    },
    {
      "x": 140,
      "y": 148,
      "t": 980643,
      "c": 2047
    },
    {
      "x": 139,
      "y": 150,
      "t": 980648,
      "c": 2047
    },
    {
      "x": 139,
      "y": 151,
      "t": 980685,
      "c": 2047
    },
    {
      "x": 140,
      "y": 151,
      "t": 980774,
      "c": 2047
    },
    {
      "x": 140,
      "y": 146,
      "t": 980781,
      "c": 2047
    },
    {
      "x": 145,
      "y": 151,
      "t": 980866,
      "c": 2047
    },
    {
      "x": 148,
      "y": 154,
      "t": 980884,
      "c": 2047
    },
    {
      "x": 148,
      "y": 155,
      "t": 980901,
      "c": 2047
    },
    {
      "x": 148,
      "y": 156,
      "t": 980941,
      "c": 2047
    },
    {
      "x": 150,
      "y": 160,
      "t": 980982,
      "c": 2047
    },
    {
      "x": 152,
      "y": 169,
      "t": 981022,
      "c": 2047
    },
    {
      "x": 158,
      "y": 177,
      "t": 981115,
      "c": 2047
    },
    {
      "x": 159,
      "y": 180,
      "t": 981133,
      "c": 2047
    },
    {
      "x": 161,
      "y": 186,
      "t": 981192,
      "c": 2047
    },
    {
      "x": 168,
      "y": 192,
      "t": 981257,
      "c": 2047
    },
    {
      "x": 169,
      "y": 191,
      "t": 981273,
      "c": 2047
    },
    {
      "x": 171,
      "y": 197,
      "t": 981298,
      "c": 2047
    },
    {
      "x": 191,
      "y": 228,
      "t": 981626,
      "c": 2047
    },
    {
      "x": 195,
      "y": 235,
      "t": 981686,
      "c": 2047
    },
    {
      "x": 193,
      "y": 234,
      "t": 981690,
      "c": 2047
    },
    {
      "x": 195,
      "y": 233,
      "t": 981721,
      "c": 2047
    },
    {
      "x": 196,
      "y": 238,
      "t": 981762,
      "c": 2047
    },
    {
      "x": 197,
      "y": 235,
      "t": 981801,
      "c": 2047
    },
    {
      "x": 197,
      "y": 239,
      "t": 981842,
      "c": 2047
    },
    {
      "x": 197,
      "y": 234,
      "t": 981883,
      "c": 2047
    },
    {
      "x": 198,
      "y": 240,
      "t": 981923,
      "c": 2047
    },
    {
      "x": 190,
      "y": 242,
      "t": 981993,
      "c": 2047
    },
    {
      "x": 189,
      "y": 235,
      "t": 982004,
      "c": 2047
    },
    {
      "x": 162,
      "y": 235,
      "t": 982198,
      "c": 2047
    },
    {
      "x": 145,
      "y": 238,
      "t": 982310,
      "c": 2047
    },
    {
      "x": 133,
      "y": 236,
      "t": 982404,
      "c": 2047
    },
    {
      "x": 129,
      "y": 234,
      "t": 982438,
      "c": 2047
    },
    {
      "x": 120,
      "y": 235,
      "t": 982491,
      "c": 2047
    },
    {
      "x": 113,
      "y": 231,
      "t": 982574,
      "c": 2047
    },
    {
      "x": 104,
      "y": 234,
      "t": 982670,
      "c": 2047
    },
    {
      "x": 100,
      "y": 234,
      "t": 982703,
      "c": 2047
    },
    {
      "x": 85,
      "y": 235,
      "t": 982837,
      "c": 2047
    },
    {
      "x": 85,
      "y": 238,
      "t": 982849,
      "c": 2047
    },
    {
      "x": 82,
      "y": 237,
      "t": 982868,
      "c": 2047
    },
    {
      "x": 75,
      "y": 237,
      "t": 982919,
      "c": 2047
    },
    {
      "x": 66,
      "y": 239,
      "t": 982970,
      "c": 2047
    },
    {
      "x": 63,
      "y": 238,
      "t": 982992,
      "c": 2047
    },
    {
      "x": 51,
      "y": 241,
      "t": 983084,
      "c": 2047
    }
  ]
}